pyawsutils/__init__.py
pyawsutils/aws_ca_cert.py
pyawsutils/aws_cloudformation.py
pyawsutils/aws_lambda.py
pyawsutils/aws_services.py
pyawsutils/clean.py
pyawsutils/cli_pyaws.py
pyawsutils/logfilters.py
pyawsutils/logging.yaml
pyawsutils/mar.py
pyawsutils/policy.py
pyawsutils/pyaws_errors.py
pyawsutils/register_signer.py
pyawsutils/status_codes.py
pyawsutils/aws_cf/custom_cf_template.json
pyawsutils/aws_cf/custom_lambdapack.zip
pyawsutils/aws_iot_policies/zt_policy.json
pyawsutils/ca_certs/AmazonRootCA1.pem
pyawsutils/ca_certs/AmazonRootCA3.pem
pyawsutils/ca_certs/G2-RootCA1.pem
pyawsutils/ca_certs/G2-RootCA3.pem
pyawsutils/ca_certs/G2-RootCA4.pem
pyawsutils/ca_certs/SFSRootCAG2.pem
pyawsutils/ca_certs/aws_ca_bundle.pem
pyawsutils-1.2.6.12.dist-info/LICENSE.txt
pyawsutils-1.2.6.12.dist-info/METADATA
pyawsutils-1.2.6.12.dist-info/WHEEL
pyawsutils-1.2.6.12.dist-info/entry_points.txt
pyawsutils-1.2.6.12.dist-info/top_level.txt
pyawsutils-1.2.6.12.dist-info/RECORD
