Metadata-Version: 2.1
Name: pyawsutils
Version: 1.2.6.12
Summary: A collection of utilities for interacting with Amazon Web Services
Author-email: Microchip Technology <support@microchip.com>
License: MIT
Project-URL: Homepage, https://github.com/microchip-pic-avr-tools/pyawsutils
Keywords: Microchip,AWS,AVR-IOT,PIC-IOT
Classifier: Development Status :: 5 - Production/Stable
Classifier: Intended Audience :: Developers
Classifier: Topic :: Software Development :: Embedded Systems
Classifier: Programming Language :: Python :: 3
Classifier: Programming Language :: Python :: 3.8
Classifier: Programming Language :: Python :: 3.9
Classifier: Programming Language :: Python :: 3.10
Classifier: Programming Language :: Python :: 3.11
Classifier: Operating System :: Microsoft :: Windows
Classifier: Operating System :: POSIX :: Linux
Classifier: Operating System :: MacOS
Classifier: License :: OSI Approved :: MIT License
Requires-Python: >=3.8
License-File: LICENSE.txt
Requires-Dist: boto3 >=1.15.2
Requires-Dist: cryptography
Requires-Dist: pyOpenSSL
Requires-Dist: packaging >=20.0
Requires-Dist: pyyaml
Requires-Dist: appdirs
Requires-Dist: pytrustplatform >=0.13
Provides-Extra: dev
Requires-Dist: pylint >=2.15 ; extra == 'dev'
Provides-Extra: doc
Requires-Dist: mock ; extra == 'doc'
Requires-Dist: sphinx ; extra == 'doc'
Provides-Extra: test
Requires-Dist: mock ; extra == 'test'
Requires-Dist: pytest ; extra == 'test'
